{
	"moves": [
		{
			"pgn": "Nc6",
			"type": 0,
			"info": " 나이트를 전개하여 e5폰을 지키고 센터 힘을 강화한다.",
			"title": "King’s Knight Opening: Main Line"
		},
		{
			"info": " e5폰을 지키지 않고 흑도 똑같이 나이트를 전개하여 백의 e4폰을 공격한다.",
			"type": 1,
			"title": "Petrov’s Defense",
			"pgn": "Nf6"
		},
		{
			"pgn": "d6",
			"type": 1,
			"title": "Philidor Defense",
			"info": " e5폰을 d열 폰을 올려 방어한다.\n 어두운 비숍길이 막힌다는 단점이 있다."
		},
		{
			"type": 4,
			"info": " e5폰을 수비해주는 듯이 보이지만 Nxe5가 가능하다.\n f폰을 밀었기 때문에 킹이 위험해지고 나이트의 가장 좋은 전개위치가 막힌다.",
			"title": "Damiano Defense",
			"pgn": "f6"
		}
	],
	"info": " 나이트를 전개하여 e5폰을 공격하고, 센터 힘을 강화하고, 캐슬링을 준비한다.",
	"title": "King’s Knight Opening"
}